{
  "version": 0.6,
  "generator": "Overpass API 0.7.55.1011 6c2efc30",
  "osm3s": {
    "timestamp_osm_base": "2020-02-06T11:33:02Z",
    "copyright": "The data included in this document is from www.openstreetmap.org. The data is made available under ODbL."
  },
  "elements": [

{
  "type": "node",
  "id": 270728862,
  "lat": 48.7204508,
  "lon": 21.2548102,
  "tags": {
    "air_conditioning": "yes",
    "contact:email": "pivovargolem@gmail.com",
    "contact:phone": "+421 55 7289 102",
    "craft": "brewery",
    "email": "pivovargolem@gmail.com",
    "is_in": "Košice I, Košický kraj, Východné Slovensko, Slovensko",
    "microbrewery": "yes",
    "name": "Golem",
    "opening_hours": "Mo-Th 11:00-23:00; Fr 11:00-01:00; Sa 17:00-01:00",
    "outdoor_seating": "yes",
    "phone": "+421 55 728 9102",
    "website": "http://www.pivovargolem.sk/",
    "wheelchair": "yes"
  }
},
{
  "type": "node",
  "id": 299700939,
  "lat": 48.7224996,
  "lon": 21.2592322,
  "tags": {
    "air_conditioning": "yes",
    "amenity": "restaurant",
    "bar": "yes",
    "brewery": "yes",
    "email": "manager@restaurant-camelot.sk",
    "microbrewery": "yes",
    "name": "Camelot",
    "opening_hours": "Mo-Su 11:00-00:00",
    "outdoor_seating": "yes",
    "phone": "+421 903 580 580",
    "reservation": "yes",
    "website": "https://www.restaurant-camelot.sk/",
    "wheelchair": "yes"
  }
},
{
  "type": "node",
  "id": 2903071120,
  "lat": 48.9899429,
  "lon": 21.2304145,
  "tags": {
    "amenity": "restaurant",
    "microbrewery": "yes",
    "name": "Mladosť",
    "opening_hours": "Mo-Sa 09:00-21:30"
  }
},
{
  "type": "node",
  "id": 3467597593,
  "lat": 48.7250975,
  "lon": 21.2550390,
  "tags": {
    "amenity": "pub",
    "craft": "brewery",
    "microbrewery": "yes",
    "name": "Red Nose Pub",
    "opening_hours": "16:00-02:00",
    "website": "http://www.rnp.sk"
  }
},
{
  "type": "node",
  "id": 3470963877,
  "lat": 48.7234644,
  "lon": 21.2579047,
  "tags": {
    "air_conditioning": "yes",
    "alt_name": "Šemrák",
    "amenity": "pub",
    "brewery": "yes",
    "contact:facebook": "https://www.facebook.com/LUXOR-brewhouse-265249070265471/",
    "email": "pivarenluxor@gmail.com",
    "internet_access": "wlan",
    "internet_access:fee": "no",
    "microbrewery": "yes",
    "name": "Luxor",
    "opening_hours": "Mo-Th 16:00-24:00; Fr-Sa 16:00-02:00; Su 16:00-24:00",
    "operator": "Phobos Group, s.r.o",
    "payment:cash": "yes",
    "payment:coins": "yes",
    "payment:credit_cards": "yes",
    "payment:debit_cards": "yes",
    "phone": "+421 950 375 652",
    "website": "https://www.pivarenluxor.sk/",
    "wheelchair": "limited"
  }
},
{
  "type": "node",
  "id": 3621162064,
  "lat": 48.9968933,
  "lon": 21.2403579,
  "tags": {
    "addr:housenumber": "65",
    "addr:street": "Hlavná",
    "amenity": "restaurant",
    "craft": "brewery",
    "microbrewery": "yes",
    "name": "Prešovský pivovar& piváreň",
    "source": "survey",
    "website": "http://www.presovskypivovar.sk"
  }
},
{
  "type": "node",
  "id": 3758792397,
  "lat": 48.7220396,
  "lon": 21.2577525,
  "tags": {
    "air_conditioning": "yes",
    "craft": "brewery",
    "email": "manager.hostinec@gmail.com",
    "microbrewery": "yes",
    "name": "Pivovar Hostinec",
    "opening_hours": "Mo-Th 11:00-00:00; Fr 14:00-02:00; Sa 14:00-01:00; Sa 12:00-00:00",
    "phone": "+421 902 580 580",
    "real_ale": "yes",
    "reservation": "yes",
    "website": "http://www.pivovarhostinec.sk/",
    "wheelchair": "yes"
  }
},
{
  "type": "node",
  "id": 5233416380,
  "lat": 48.7296587,
  "lon": 21.2520731,
  "tags": {
    "craft": "brewery",
    "name": "Pivovarský dvor Corvus",
    "note": "Outdoor seating only during summer.",
    "opening_hours": "Mo-Su 09:00-23:45",
    "operator": "Pivovar Corvus s.r.o.",
    "outdoor_seating": "yes",
    "smoking": "outside",
    "website": "https://www.corvusbrewery.sk/",
    "wheelchair": "limited"
  }
},
{
  "type": "node",
  "id": 5323496421,
  "lat": 48.7215025,
  "lon": 21.2568525,
  "tags": {
    "craft": "brewery",
    "name": "Korzo"
  }
},
{
  "type": "node",
  "id": 5652465004,
  "lat": 48.6811151,
  "lon": 21.1686037,
  "tags": {
    "addr:city": "Malá Ida",
    "addr:housenumber": "1",
    "addr:postcode": "044 20",
    "addr:street": "Nevädzová",
    "contact:facebook": "https://www.facebook.com/herrenwald/",
    "contact:instagram": "https://www.instagram.com/herrenwald.pivovar/",
    "craft": "brewery",
    "cuisine": "regional",
    "email": "info@herrenwald.sk",
    "microbrewery": "yes",
    "name": "Herrenwald",
    "operator": "Herrenwald s.r.o.",
    "phone": "+421 911 700 750",
    "product": "beer",
    "website": "http://www.herrenwald.sk/",
    "wheelchair": "yes"
  }
},
{
  "type": "node",
  "id": 6565064236,
  "lat": 48.7189680,
  "lon": 21.2584540,
  "tags": {
    "amenity": "pub",
    "brewery": "yes",
    "microbrewery": "yes",
    "name": "Žil verne"
  }
},
{
  "type": "way",
  "id": 723231401,
  "nodes": [
    6266450712,
    6266450727,
    6266450713,
    6266450726,
    6266450714,
    6266450725,
    6266450715,
    6266450724,
    6266450716,
    6266450723,
    6782307767,
    6266450735,
    6266450721,
    6266450734,
    6266450718,
    6266450732,
    6266450722,
    6266450733,
    6266450719,
    6783586685,
    6783582437,
    6783582472,
    6783582473,
    6783582474,
    6783582475,
    6783611044,
    6783611043,
    6783582476,
    6783582477,
    6783582478,
    6266450708,
    6783611042,
    6783582458,
    6266450731,
    6266450709,
    6266450730,
    6266450710,
    6266450729,
    6266450711,
    6296627513,
    6782307772,
    6266450728,
    6266450712
  ],
  "tags": {
    "air_conditioning": "yes",
    "amenity": "pub",
    "area": "yes",
    "brewery": "various",
    "indoor": "room",
    "level": "2",
    "microbrewery": "yes",
    "name": "Staničný Pivovar",
    "opening_hours": "Mo-Th 10:00-20:00; Fr 10:00-00:00; Sa-Su 10:00-22:00",
    "outdoor_seating": "yes",
    "payment:cash": "yes",
    "payment:coins": "yes",
    "payment:credit_cards": "yes",
    "payment:debit_cards": "yes",
    "phone": "+421 918 117 428",
    "room": "restaurant",
    "smoking": "outside",
    "wheelchair": "yes"
  }
},
{
  "type": "node",
  "id": 6266450708,
  "lat": 48.7226670,
  "lon": 21.2675554
},
{
  "type": "node",
  "id": 6266450709,
  "lat": 48.7226953,
  "lon": 21.2675165
},
{
  "type": "node",
  "id": 6266450710,
  "lat": 48.7227227,
  "lon": 21.2674736
},
{
  "type": "node",
  "id": 6266450711,
  "lat": 48.7227448,
  "lon": 21.2674280
},
{
  "type": "node",
  "id": 6266450713,
  "lat": 48.7227325,
  "lon": 21.2673650
},
{
  "type": "node",
  "id": 6266450714,
  "lat": 48.7226986,
  "lon": 21.2673784
},
{
  "type": "node",
  "id": 6266450715,
  "lat": 48.7226650,
  "lon": 21.2673985
},
{
  "type": "node",
  "id": 6266450716,
  "lat": 48.7226334,
  "lon": 21.2674280
},
{
  "type": "node",
  "id": 6266450718,
  "lat": 48.7225551,
  "lon": 21.2675393
},
{
  "type": "node",
  "id": 6266450719,
  "lat": 48.7225095,
  "lon": 21.2676318
},
{
  "type": "node",
  "id": 6266450721,
  "lat": 48.7225755,
  "lon": 21.2675049
},
{
  "type": "node",
  "id": 6266450722,
  "lat": 48.7225330,
  "lon": 21.2675816
},
{
  "type": "node",
  "id": 6266450723,
  "lat": 48.7226149,
  "lon": 21.2674479
},
{
  "type": "node",
  "id": 6266450724,
  "lat": 48.7226479,
  "lon": 21.2674132
},
{
  "type": "node",
  "id": 6266450725,
  "lat": 48.7226814,
  "lon": 21.2673878
},
{
  "type": "node",
  "id": 6266450726,
  "lat": 48.7227151,
  "lon": 21.2673717
},
{
  "type": "node",
  "id": 6266450727,
  "lat": 48.7227484,
  "lon": 21.2673616
},
{
  "type": "node",
  "id": 6266450729,
  "lat": 48.7227342,
  "lon": 21.2674515
},
{
  "type": "node",
  "id": 6266450730,
  "lat": 48.7227099,
  "lon": 21.2674957
},
{
  "type": "node",
  "id": 6266450731,
  "lat": 48.7226811,
  "lon": 21.2675366
},
{
  "type": "node",
  "id": 6266450732,
  "lat": 48.7225442,
  "lon": 21.2675601
},
{
  "type": "node",
  "id": 6266450733,
  "lat": 48.7225212,
  "lon": 21.2676070
},
{
  "type": "node",
  "id": 6266450734,
  "lat": 48.7225653,
  "lon": 21.2675218
},
{
  "type": "node",
  "id": 6266450735,
  "lat": 48.7225862,
  "lon": 21.2674867
},
{
  "type": "node",
  "id": 6296627513,
  "lat": 48.7227518,
  "lon": 21.2674077
},
{
  "type": "node",
  "id": 6782307767,
  "lat": 48.7225990,
  "lon": 21.2674674
},
{
  "type": "node",
  "id": 6783582437,
  "lat": 48.7224849,
  "lon": 21.2676993
},
{
  "type": "node",
  "id": 6783582458,
  "lat": 48.7226716,
  "lon": 21.2675379
},
{
  "type": "node",
  "id": 6783582472,
  "lat": 48.7225260,
  "lon": 21.2676757
},
{
  "type": "node",
  "id": 6783582473,
  "lat": 48.7225554,
  "lon": 21.2676586
},
{
  "type": "node",
  "id": 6783582474,
  "lat": 48.7225703,
  "lon": 21.2676493
},
{
  "type": "node",
  "id": 6783582475,
  "lat": 48.7225847,
  "lon": 21.2676393
},
{
  "type": "node",
  "id": 6783582476,
  "lat": 48.7226182,
  "lon": 21.2676132
},
{
  "type": "node",
  "id": 6783582477,
  "lat": 48.7226318,
  "lon": 21.2675985
},
{
  "type": "node",
  "id": 6783582478,
  "lat": 48.7226474,
  "lon": 21.2675808
},
{
  "type": "node",
  "id": 6783586685,
  "lat": 48.7224979,
  "lon": 21.2676638
},
{
  "type": "node",
  "id": 6783611042,
  "lat": 48.7226693,
  "lon": 21.2675467
},
{
  "type": "node",
  "id": 6783611043,
  "lat": 48.7226102,
  "lon": 21.2676207
},
{
  "type": "node",
  "id": 6783611044,
  "lat": 48.7225977,
  "lon": 21.2676305
},
{
  "type": "node",
  "id": 6266450712,
  "lat": 48.7227652,
  "lon": 21.2673583
},
{
  "type": "node",
  "id": 6266450728,
  "lat": 48.7227614,
  "lon": 21.2673757
},
{
  "type": "node",
  "id": 6782307772,
  "lat": 48.7227587,
  "lon": 21.2673864
}

  ]
}
