{
  "version": 0.6,
  "generator": "Overpass API 0.7.55.9 ab41fea6",
  "osm3s": {
    "timestamp_osm_base": "2020-02-06T01:02:03Z",
    "copyright": "The data included in this document is from www.openstreetmap.org. The data is made available under ODbL."
  },
  "elements": [

{
  "type": "node",
  "id": 3149701714,
  "lat": 49.6417165,
  "lon": 17.2310552,
  "tags": {
    "amenity": "restaurant",
    "cuisine": "regional",
    "internet_access": "wlan",
    "microbrewery": "yes",
    "name": "Pivovar Chomout",
    "phone": "608778348",
    "smoking": "no",
    "website": "https://www.pivochomout.cz/"
  }
},
{
  "type": "node",
  "id": 3152867242,
  "lat": 49.6305819,
  "lon": 17.3389873,
  "tags": {
    "contact:website": "http://www.svatokopeckepivo.cz/",
    "craft": "brewery",
    "microbrewery": "yes",
    "name": "Svatokopecké Pivo"
  }
},
{
  "type": "node",
  "id": 3978068599,
  "lat": 49.6126285,
  "lon": 16.6863819,
  "tags": {
    "addr:conscriptionnumber": "771",
    "addr:housenumber": "771",
    "addr:place": "Velké Opatovice",
    "addr:postcode": "67963",
    "addr:street": "Rybník",
    "amenity": "pub",
    "microbrewery": "yes",
    "name": "Hospoda na hřišti",
    "ref:ruian:addr": "74471341"
  }
},
{
  "type": "node",
  "id": 4591233993,
  "lat": 49.2831577,
  "lon": 17.1714404,
  "tags": {
    "addr:housenumber": "57",
    "addr:place": "Koválovice u Tištína",
    "amenity": "restaurant",
    "microbrewery": "yes",
    "name": "Řemeslný pivovar Husar",
    "name:cs": "Řemeslný pivovar Husar",
    "website": "https://www.pivohusar.cz/"
  }
},
{
  "type": "node",
  "id": 4591240594,
  "lat": 49.2786883,
  "lon": 17.0407385,
  "tags": {
    "addr:housenumber": "19",
    "addr:street": "Topolany",
    "amenity": "restaurant",
    "microbrewery": "yes",
    "name": "Minipivovar Lišák"
  }
},
{
  "type": "node",
  "id": 4844372714,
  "lat": 49.6011236,
  "lon": 17.0681731,
  "tags": {
    "craft": "brewery",
    "name": "Palírna \"U Jadrníčků\""
  }
},
{
  "type": "node",
  "id": 4929260240,
  "lat": 49.2891804,
  "lon": 17.4904704,
  "tags": {
    "craft": "brewery",
    "name": "Pivovar Záhlinice"
  }
},
{
  "type": "way",
  "id": 143760345,
  "nodes": [
    1573099957,
    5910129445,
    1573099964,
    5910129443,
    1573100017,
    1573100023,
    1571400568,
    3430765464,
    3430765461,
    3430765462,
    1573099914,
    1573099900,
    5046927955,
    1573099931,
    1573099926,
    1573099896,
    1573099893,
    1573099890,
    1573099870,
    5910129447,
    1573099957
  ],
  "tags": {
    "addr:housenumber": "1652/4a",
    "addr:street": "Újezd",
    "amenity": "restaurant",
    "building": "yes",
    "email": "restaurant@ukralejecminka.cz",
    "microbrewery": "yes",
    "name": "U krále Ječmínka",
    "phone": "+420582346401",
    "source": "cuzk:km",
    "website": "http://www.ukralejecminka.cz/"
  }
},
{
  "type": "way",
  "id": 180672102,
  "nodes": [
    1911188827,
    1911188821,
    1911188819,
    1911188811,
    1911188807,
    1911188802,
    1911188804,
    1911188793,
    1911188790,
    1911188800,
    1911188825,
    1911188827
  ],
  "tags": {
    "amenity": "pub",
    "building": "yes",
    "microbrewery": "yes",
    "name": "Chomout",
    "outdoor_seating": "yes",
    "source": "cuzk:km"
  }
},
{
  "type": "way",
  "id": 180672104,
  "nodes": [
    1911188813,
    1911188815,
    1911188809,
    1911188798,
    1911188787,
    1911188773,
    1911188775,
    1911188779,
    1911188796,
    1911188805,
    1911188817,
    1911188813
  ],
  "tags": {
    "building": "yes",
    "craft": "brewery",
    "name": "Chomout",
    "source": "cuzk:km"
  }
},
{
  "type": "way",
  "id": 215235490,
  "nodes": [
    2246404187,
    2246404196,
    2246404175,
    2246404169,
    2246404158,
    2246404151,
    2246404137,
    2246404082,
    2246404164,
    2246404172,
    2246404185,
    2246404208,
    2246404201,
    2246404219,
    2246404187
  ],
  "tags": {
    "building": "yes",
    "craft": "brewery",
    "name": "Minipivovar Svatovar",
    "source": "cuzk:km"
  }
},
{
  "type": "way",
  "id": 499667141,
  "nodes": [
    4909121872,
    4929183464,
    4909121871,
    4909121870,
    4909121869,
    4909121868,
    4909121867,
    4909121866,
    4909121865,
    4909121864,
    4909121863,
    4909121862,
    4909121861,
    4909121860,
    4909121877,
    4909121876,
    4909121875,
    4909121874,
    4909121873,
    4909121872
  ],
  "tags": {
    "craft": "brewery",
    "landuse": "industrial",
    "name": "Bývalý Akciový pivovar Prostějov"
  }
},
{
  "type": "node",
  "id": 1571400568,
  "lat": 49.4723817,
  "lon": 17.1163612
},
{
  "type": "node",
  "id": 1573099870,
  "lat": 49.4721848,
  "lon": 17.1168503
},
{
  "type": "node",
  "id": 1573099890,
  "lat": 49.4721860,
  "lon": 17.1168100
},
{
  "type": "node",
  "id": 1573099893,
  "lat": 49.4721900,
  "lon": 17.1167710
},
{
  "type": "node",
  "id": 1573099896,
  "lat": 49.4722071,
  "lon": 17.1165092
},
{
  "type": "node",
  "id": 1573099900,
  "lat": 49.4722100,
  "lon": 17.1164180
},
{
  "type": "node",
  "id": 1573099914,
  "lat": 49.4722180,
  "lon": 17.1163600
},
{
  "type": "node",
  "id": 1573099926,
  "lat": 49.4722280,
  "lon": 17.1165123
},
{
  "type": "node",
  "id": 1573099931,
  "lat": 49.4722347,
  "lon": 17.1164453
},
{
  "type": "node",
  "id": 1573099957,
  "lat": 49.4722678,
  "lon": 17.1168245
},
{
  "type": "node",
  "id": 1573099964,
  "lat": 49.4722930,
  "lon": 17.1164450
},
{
  "type": "node",
  "id": 1573100017,
  "lat": 49.4724035,
  "lon": 17.1164450
},
{
  "type": "node",
  "id": 1573100023,
  "lat": 49.4724050,
  "lon": 17.1163645
},
{
  "type": "node",
  "id": 3430765461,
  "lat": 49.4723357,
  "lon": 17.1163654
},
{
  "type": "node",
  "id": 3430765462,
  "lat": 49.4723363,
  "lon": 17.1163607
},
{
  "type": "node",
  "id": 3430765464,
  "lat": 49.4723812,
  "lon": 17.1163659
},
{
  "type": "node",
  "id": 5046927955,
  "lat": 49.4722241,
  "lon": 17.1164397
},
{
  "type": "node",
  "id": 5910129443,
  "lat": 49.4723962,
  "lon": 17.1164450
},
{
  "type": "node",
  "id": 5910129445,
  "lat": 49.4722790,
  "lon": 17.1166668
},
{
  "type": "node",
  "id": 5910129447,
  "lat": 49.4721984,
  "lon": 17.1168539
},
{
  "type": "node",
  "id": 4909121876,
  "lat": 49.4778735,
  "lon": 17.1310724
},
{
  "type": "node",
  "id": 4909121872,
  "lat": 49.4760603,
  "lon": 17.1321687
},
{
  "type": "node",
  "id": 4909121860,
  "lat": 49.4781412,
  "lon": 17.1312191
},
{
  "type": "node",
  "id": 4909121861,
  "lat": 49.4780936,
  "lon": 17.1313553
},
{
  "type": "node",
  "id": 4909121862,
  "lat": 49.4780414,
  "lon": 17.1315159
},
{
  "type": "node",
  "id": 4909121863,
  "lat": 49.4779881,
  "lon": 17.1316584
},
{
  "type": "node",
  "id": 4909121864,
  "lat": 49.4778785,
  "lon": 17.1319150
},
{
  "type": "node",
  "id": 4909121865,
  "lat": 49.4778205,
  "lon": 17.1321389
},
{
  "type": "node",
  "id": 4909121866,
  "lat": 49.4778103,
  "lon": 17.1322920
},
{
  "type": "node",
  "id": 4909121867,
  "lat": 49.4777882,
  "lon": 17.1329143
},
{
  "type": "node",
  "id": 4909121868,
  "lat": 49.4775699,
  "lon": 17.1335041
},
{
  "type": "node",
  "id": 4909121869,
  "lat": 49.4771453,
  "lon": 17.1341916
},
{
  "type": "node",
  "id": 4909121870,
  "lat": 49.4768975,
  "lon": 17.1346041
},
{
  "type": "node",
  "id": 4909121871,
  "lat": 49.4767695,
  "lon": 17.1347062
},
{
  "type": "node",
  "id": 4909121873,
  "lat": 49.4770963,
  "lon": 17.1315840
},
{
  "type": "node",
  "id": 4909121874,
  "lat": 49.4770688,
  "lon": 17.1315070
},
{
  "type": "node",
  "id": 4909121875,
  "lat": 49.4776236,
  "lon": 17.1311917
},
{
  "type": "node",
  "id": 4909121877,
  "lat": 49.4781559,
  "lon": 17.1311817
},
{
  "type": "node",
  "id": 4929183464,
  "lat": 49.4765472,
  "lon": 17.1339107
},
{
  "type": "node",
  "id": 1911188773,
  "lat": 49.6416230,
  "lon": 17.2311610
},
{
  "type": "node",
  "id": 1911188775,
  "lat": 49.6416480,
  "lon": 17.2311410
},
{
  "type": "node",
  "id": 1911188779,
  "lat": 49.6416710,
  "lon": 17.2312200
},
{
  "type": "node",
  "id": 1911188787,
  "lat": 49.6416755,
  "lon": 17.2313430
},
{
  "type": "node",
  "id": 1911188790,
  "lat": 49.6416810,
  "lon": 17.2310150
},
{
  "type": "node",
  "id": 1911188793,
  "lat": 49.6416940,
  "lon": 17.2311140
},
{
  "type": "node",
  "id": 1911188796,
  "lat": 49.6417130,
  "lon": 17.2311990
},
{
  "type": "node",
  "id": 1911188798,
  "lat": 49.6417240,
  "lon": 17.2314190
},
{
  "type": "node",
  "id": 1911188800,
  "lat": 49.6417280,
  "lon": 17.2310010
},
{
  "type": "node",
  "id": 1911188802,
  "lat": 49.6417390,
  "lon": 17.2310910
},
{
  "type": "node",
  "id": 1911188804,
  "lat": 49.6417400,
  "lon": 17.2311010
},
{
  "type": "node",
  "id": 1911188805,
  "lat": 49.6417440,
  "lon": 17.2312860
},
{
  "type": "node",
  "id": 1911188807,
  "lat": 49.6418100,
  "lon": 17.2310850
},
{
  "type": "node",
  "id": 1911188809,
  "lat": 49.6418110,
  "lon": 17.2315390
},
{
  "type": "node",
  "id": 1911188811,
  "lat": 49.6418150,
  "lon": 17.2311640
},
{
  "type": "node",
  "id": 1911188813,
  "lat": 49.6418250,
  "lon": 17.2314860
},
{
  "type": "node",
  "id": 1911188815,
  "lat": 49.6418350,
  "lon": 17.2314990
},
{
  "type": "node",
  "id": 1911188817,
  "lat": 49.6418500,
  "lon": 17.2314480
},
{
  "type": "node",
  "id": 1911188819,
  "lat": 49.6418550,
  "lon": 17.2311590
},
{
  "type": "node",
  "id": 1911188821,
  "lat": 49.6418810,
  "lon": 17.2313980
},
{
  "type": "node",
  "id": 1911188825,
  "lat": 49.6419100,
  "lon": 17.2309860
},
{
  "type": "node",
  "id": 1911188827,
  "lat": 49.6419460,
  "lon": 17.2313780
},
{
  "type": "node",
  "id": 2246404082,
  "lat": 49.5265140,
  "lon": 17.5892360
},
{
  "type": "node",
  "id": 2246404137,
  "lat": 49.5265790,
  "lon": 17.5893200
},
{
  "type": "node",
  "id": 2246404151,
  "lat": 49.5265860,
  "lon": 17.5893030
},
{
  "type": "node",
  "id": 2246404158,
  "lat": 49.5265950,
  "lon": 17.5893080
},
{
  "type": "node",
  "id": 2246404164,
  "lat": 49.5265980,
  "lon": 17.5890880
},
{
  "type": "node",
  "id": 2246404169,
  "lat": 49.5266140,
  "lon": 17.5892750
},
{
  "type": "node",
  "id": 2246404172,
  "lat": 49.5266200,
  "lon": 17.5891180
},
{
  "type": "node",
  "id": 2246404175,
  "lat": 49.5266210,
  "lon": 17.5892830
},
{
  "type": "node",
  "id": 2246404185,
  "lat": 49.5266290,
  "lon": 17.5891000
},
{
  "type": "node",
  "id": 2246404187,
  "lat": 49.5266290,
  "lon": 17.5892460
},
{
  "type": "node",
  "id": 2246404196,
  "lat": 49.5266360,
  "lon": 17.5892560
},
{
  "type": "node",
  "id": 2246404201,
  "lat": 49.5266440,
  "lon": 17.5891480
},
{
  "type": "node",
  "id": 2246404208,
  "lat": 49.5266500,
  "lon": 17.5891310
},
{
  "type": "node",
  "id": 2246404219,
  "lat": 49.5266660,
  "lon": 17.5891760
}

  ]
}
